dometawrite/__init__.py
dometawrite/dometawrite.py
dometawrite/templates/authorizedkeys.jinja
dometawrite/templates/debug.jinja
dometawrite/templates/droplet_envvars.jinja
dometawrite/templates/sshconfig.jinja
dometawrite-0.1.14.dist-info/DESCRIPTION.rst
dometawrite-0.1.14.dist-info/METADATA
dometawrite-0.1.14.dist-info/RECORD
dometawrite-0.1.14.dist-info/WHEEL
dometawrite-0.1.14.dist-info/entry_points.txt
dometawrite-0.1.14.dist-info/metadata.json
dometawrite-0.1.14.dist-info/top_level.txt
