Metadata-Version: 2.0
Name: dometawrite
Version: 0.1.14
Summary: Creates configuration files based on DigitalOcean API Data.
Home-page: https://github.com/buanzo/digitalocean-metawrite
Author: Arturo "Buanzo" Busleiman
Author-email: buanzo@buanzo.com.ar
License: GPLv3
Keywords: configuration,api,templates,digitalocean,devops,sysadmin
Platform: UNKNOWN
Classifier: Environment :: Console
Classifier: Intended Audience :: Developers
Classifier: Intended Audience :: System Administrators
Classifier: License :: OSI Approved :: GNU General Public License v3 (GPLv3)
Classifier: Natural Language :: English
Classifier: Operating System :: POSIX :: Linux
Classifier: Operating System :: POSIX :: Other
Classifier: Operating System :: POSIX
Classifier: Programming Language :: Python
Classifier: Programming Language :: Python :: 3 :: Only
Classifier: Programming Language :: Python :: 3.6
Classifier: Programming Language :: Python :: 3.7
Classifier: Programming Language :: Python :: 3.8
Classifier: Programming Language :: Python :: Implementation :: PyPy
Requires-Python: >=3.6
Requires-Dist: Jinja2 (>=2.10.1)
Requires-Dist: requests (>=2.20.0)
